ozzy/__init__.py
ozzy/accessors.py
ozzy/backend_interface.py
ozzy/backends/__init__.py
ozzy/backends/lcode_backend.py
ozzy/backends/lcode_file_key.csv
ozzy/backends/osiris_backend.py
ozzy/backends/ozzy_backend.py
ozzy/backends/template_backend.py
ozzy/core.py
ozzy/fields.py
ozzy/fonts/Crimson_Pro/CrimsonPro-Italic-VariableFont_wght.ttf
ozzy/fonts/Crimson_Pro/CrimsonPro-VariableFont_wght.ttf
ozzy/fonts/Crimson_Pro/OFL.txt
ozzy/fonts/Crimson_Pro/README.txt
ozzy/fonts/Maitree/Maitree-Bold.ttf
ozzy/fonts/Maitree/Maitree-ExtraLight.ttf
ozzy/fonts/Maitree/Maitree-Light.ttf
ozzy/fonts/Maitree/Maitree-Medium.ttf
ozzy/fonts/Maitree/Maitree-Regular.ttf
ozzy/fonts/Maitree/Maitree-SemiBold.ttf
ozzy/fonts/Maitree/OFL.txt
"ozzy/fonts/Noto_Serif/NotoSerif-Italic-VariableFont_wdth,wght.ttf"
"ozzy/fonts/Noto_Serif/NotoSerif-VariableFont_wdth,wght.ttf"
ozzy/fonts/Noto_Serif/OFL.txt
ozzy/fonts/Noto_Serif/README.txt
ozzy/fonts/Roboto_Serif/OFL.txt
ozzy/fonts/Roboto_Serif/README.txt
"ozzy/fonts/Roboto_Serif/RobotoSerif-Italic-VariableFont_GRAD,opsz,wdth,wght.ttf"
"ozzy/fonts/Roboto_Serif/RobotoSerif-VariableFont_GRAD,opsz,wdth,wght.ttf"
ozzy/fonts/STIX_Two_Text/OFL.txt
ozzy/fonts/STIX_Two_Text/README.txt
ozzy/fonts/STIX_Two_Text/STIXTwoText-Italic-VariableFont_wght.ttf
ozzy/fonts/STIX_Two_Text/STIXTwoText-VariableFont_wght.ttf
ozzy/fonts/Source_Serif_4/OFL.txt
ozzy/fonts/Source_Serif_4/README.txt
"ozzy/fonts/Source_Serif_4/SourceSerif4-Italic-VariableFont_opsz,wght.ttf"
"ozzy/fonts/Source_Serif_4/SourceSerif4-VariableFont_opsz,wght.ttf"
ozzy/grid_mixin.py
ozzy/new_dataobj.py
ozzy/part_mixin.py
ozzy/plot.py
ozzy/statistics.py
ozzy/tol_colors.py
ozzy/utils.py
ozzy_pic-2.0.3.dist-info/LICENSE
ozzy_pic-2.0.3.dist-info/METADATA
ozzy_pic-2.0.3.dist-info/WHEEL
ozzy_pic-2.0.3.dist-info/RECORD
