Metadata-Version: 2.3
Name: ozzy-pic
Version: 2.0.3
Summary: PIC simulation data analysis for the lazy and impatient
License: MIT
Author: Mariana Moreira
Author-email: mtrocadomoreira@gmail.com
Requires-Python: >=3.10,<3.14
Classifier: Development Status :: 4 - Beta
Classifier: Framework :: Hypothesis
Classifier: Framework :: IPython
Classifier: Framework :: Jupyter
Classifier: Framework :: Jupyter :: JupyterLab
Classifier: Framework :: Matplotlib
Classifier: Framework :: MkDocs
Classifier: Framework :: Pytest
Classifier: Intended Audience :: Science/Research
Classifier: License :: OSI Approved :: MIT License
Classifier: Natural Language :: English
Classifier: Operating System :: MacOS
Classifier: Operating System :: Microsoft
Classifier: Operating System :: Unix
Classifier: Programming Language :: Python
Classifier: Programming Language :: Python :: 3
Classifier: Programming Language :: Python :: 3.10
Classifier: Programming Language :: Python :: 3.11
Classifier: Programming Language :: Python :: 3.12
Classifier: Programming Language :: Python :: 3.13
Classifier: Topic :: Scientific/Engineering :: Physics
Classifier: Topic :: Scientific/Engineering :: Visualization
Provides-Extra: interactive
Requires-Dist: cmcrameri
Requires-Dist: dask (>=2025.5.1,<2026)
Requires-Dist: dask-expr (>=2.0.0,<3)
Requires-Dist: flox (>=0.10.4,<0.11.0)
Requires-Dist: h5netcdf (>=1.6.1,<2.0.0)
Requires-Dist: h5py (>=3.14.0,<4.0.0)
Requires-Dist: hvplot (>=0.11.3,<1.0) ; extra == "interactive"
Requires-Dist: ipykernel (>=6.29.5,<7.0) ; extra == "interactive"
Requires-Dist: ipython (>=8.28.0,<9.0) ; extra == "interactive"
Requires-Dist: jupyter-bokeh (>=4.0.5,<5.0) ; extra == "interactive"
Requires-Dist: matplotlib (>=3.10.3,<4.0.0)
Requires-Dist: numba (>=0.62,<1.0)
Requires-Dist: numbagg (>=0.9.0,<0.10.0)
Requires-Dist: numpy-groupies (>=0.11.3,<0.12.0)
Requires-Dist: pyarrow (>=20.0.0,<21.0.0)
Requires-Dist: seaborn (>=0.13.2,<0.14.0)
Requires-Dist: tqdm (>=4.67.1,<5.0.0)
Requires-Dist: xarray (>=2025.6.1,<2026.0.0)
Project-URL: Documentation, https://mtrocadomoreira.github.io/ozzy/
Project-URL: Homepage, https://mtrocadomoreira.github.io/ozzy/
Project-URL: Repository, https://github.com/mtrocadomoreira/ozzy.git
